anymerge/__init__.py
anymerge/_api.py
anymerge/_merger.py
anymerge/_reducer.py
anymerge/_typing_utils.py
anymerge/exceptions.py
anymerge/models.py
anymerge/py.typed
anymerge/reducers.py
anymerge/types.py
anymerge/adapters/__init__.py
anymerge/adapters/_utils.py
anymerge/adapters/base_adapter.py
anymerge/adapters/dataclass_adapter.py
anymerge/adapters/pydantic_adapter.py
anymerge/adapters/typeddict_adapter.py
anymerge-0.0.1a0.dist-info/METADATA
anymerge-0.0.1a0.dist-info/WHEEL
anymerge-0.0.1a0.dist-info/licenses/LICENSE
anymerge-0.0.1a0.dist-info/RECORD
